gracefull_shutdown/__init__.py
gracefull_shutdown_py-0.2.1.dist-info/LICENSE
gracefull_shutdown_py-0.2.1.dist-info/METADATA
gracefull_shutdown_py-0.2.1.dist-info/WHEEL
gracefull_shutdown_py-0.2.1.dist-info/top_level.txt
gracefull_shutdown_py-0.2.1.dist-info/RECORD
