Metadata-Version: 2.1
Name: gracefull-shutdown-py
Version: 0.2.1
Summary: attr: gracefull_shutdown.__doc__
Home-page: https://github.com/zifter/gracefull-shutdown-py
Author: Aleh Strakachuk
Author-email: zifter.ai@gmail.com
License: MIT
Keywords: gracefull,shutdown
Platform: any
Classifier: Development Status :: 5 - Production/Stable
Classifier: License :: OSI Approved :: MIT License
Classifier: Programming Language :: Python
Classifier: Programming Language :: Python :: 3.5
Classifier: Programming Language :: Python :: 3.6
Classifier: Programming Language :: Python :: 3.7
Classifier: Programming Language :: Python :: 3.8
Classifier: Programming Language :: Python :: 3.9
Classifier: Programming Language :: Python :: 3.10
Classifier: Programming Language :: Python :: 3.11
Classifier: Operating System :: OS Independent
Requires-Python: >=3.5
License-File: LICENSE
